Metadata-Version: 2.1
Name: di-distr
Version: 1.0
Summary: Gaussian and Binomial distributions
Author: Diana
